{
  "id": "SHARC.Bundle",
  "category": "bundle",
  "metadata": {
    "publisher": "TrakHound Inc.",
    "description": "Collect & View Data from SHARC Sensors",
    ".image": "https://www.trakhound.com/management/static/sharc-logo"
  },
  "dependencies": [
    {
      "id": "TrakHound.Entities.Api",
      "version": "*"
    },
    {
      "id": "TrakHound.Sqlite.Drivers",
      "version": "*"
    },
    {
      "id": "TrakHound.Sqlite.TimeSeries.Drivers",
      "version": "*"
    },
    {
      "id": "SHARC.App",
      "version": "*"
    },
    {
      "id": "SHARC.Api",
      "version": "*"
    },
    {
      "id": "SHARC.Collection.Api",
      "version": "*"
    },
    {
      "id": "SHARC.Collection.Service",
      "version": "*"
    }
  ]
}